{
  "generated_at": "2026-06-30T16:53:41",
  "source": {
    "official_tag_path": "/home/local/xinyu/K-Radar/tools/tag_generator/tag_generation.py",
    "gt_root": "/home/local/xinyu/K-Radar-GT-Polar-v2"
  },
  "scope_definition": {
    "all": "Full valid GT tensor FOV: 0<=r<256, 0<=a<107, 0<=e<37.",
    "narrow": "Current project narrow scope: Cartesian ROI x:[0,72], y:[-6.4,6.4], z:[-2,6] plus azimuth [-50deg, 50deg]."
  },
  "highway_sequences": [
    2,
    3,
    4,
    9,
    10,
    11,
    12,
    13,
    46,
    47,
    48,
    49,
    50,
    51,
    52,
    53
  ],
  "weather_to_sequences": {
    "normal": [
      2,
      3,
      4,
      9,
      10,
      11,
      12
    ],
    "overcast": [
      13
    ],
    "sleet": [
      50,
      51,
      52,
      53
    ],
    "lightsnow": [
      48,
      49
    ],
    "heavysnow": [
      46,
      47
    ]
  },
  "summary": {
    "all_total": 22019,
    "narrow_total": 16523,
    "all_sedan": 14426,
    "narrow_sedan": 11130,
    "all_bus": 7593,
    "narrow_bus": 5393,
    "frames_with_gt": 8901,
    "num_highway_sequences": 16
  },
  "by_weather": {
    "normal": {
      "all_total": 16058,
      "narrow_total": 11544,
      "all_sedan": 10823,
      "narrow_sedan": 8120,
      "all_bus": 5235,
      "narrow_bus": 3424
    },
    "overcast": {
      "all_total": 407,
      "narrow_total": 402,
      "all_sedan": 305,
      "narrow_sedan": 304,
      "all_bus": 102,
      "narrow_bus": 98
    },
    "sleet": {
      "all_total": 2457,
      "narrow_total": 1875,
      "all_sedan": 2364,
      "narrow_sedan": 1800,
      "all_bus": 93,
      "narrow_bus": 75
    },
    "lightsnow": {
      "all_total": 1810,
      "narrow_total": 1547,
      "all_sedan": 500,
      "narrow_sedan": 493,
      "all_bus": 1310,
      "narrow_bus": 1054
    },
    "heavysnow": {
      "all_total": 1287,
      "narrow_total": 1155,
      "all_sedan": 434,
      "narrow_sedan": 413,
      "all_bus": 853,
      "narrow_bus": 742
    }
  },
  "by_sequence": {
    "2": {
      "road": "highway",
      "time": "night",
      "weather": "normal",
      "all_total": 93,
      "narrow_total": 71,
      "all_sedan": 1,
      "narrow_sedan": 0,
      "all_bus": 92,
      "narrow_bus": 71,
      "frames_with_gt": 98
    },
    "3": {
      "road": "highway",
      "time": "night",
      "weather": "normal",
      "all_total": 1458,
      "narrow_total": 755,
      "all_sedan": 484,
      "narrow_sedan": 226,
      "all_bus": 974,
      "narrow_bus": 529,
      "frames_with_gt": 566
    },
    "4": {
      "road": "highway",
      "time": "night",
      "weather": "normal",
      "all_total": 464,
      "narrow_total": 219,
      "all_sedan": 64,
      "narrow_sedan": 59,
      "all_bus": 400,
      "narrow_bus": 160,
      "frames_with_gt": 392
    },
    "9": {
      "road": "highway",
      "time": "day",
      "weather": "normal",
      "all_total": 2445,
      "narrow_total": 1520,
      "all_sedan": 1964,
      "narrow_sedan": 1520,
      "all_bus": 481,
      "narrow_bus": 0,
      "frames_with_gt": 833
    },
    "10": {
      "road": "highway",
      "time": "day",
      "weather": "normal",
      "all_total": 3188,
      "narrow_total": 2717,
      "all_sedan": 2478,
      "narrow_sedan": 2156,
      "all_bus": 710,
      "narrow_bus": 561,
      "frames_with_gt": 1059
    },
    "11": {
      "road": "highway",
      "time": "day",
      "weather": "normal",
      "all_total": 5449,
      "narrow_total": 4087,
      "all_sedan": 3838,
      "narrow_sedan": 2616,
      "all_bus": 1611,
      "narrow_bus": 1471,
      "frames_with_gt": 1188
    },
    "12": {
      "road": "highway",
      "time": "day",
      "weather": "normal",
      "all_total": 2961,
      "narrow_total": 2175,
      "all_sedan": 1994,
      "narrow_sedan": 1543,
      "all_bus": 967,
      "narrow_bus": 632,
      "frames_with_gt": 853
    },
    "13": {
      "road": "highway",
      "time": "day",
      "weather": "overcast",
      "all_total": 407,
      "narrow_total": 402,
      "all_sedan": 305,
      "narrow_sedan": 304,
      "all_bus": 102,
      "narrow_bus": 98,
      "frames_with_gt": 216
    },
    "46": {
      "road": "highway",
      "time": "night",
      "weather": "heavysnow",
      "all_total": 1029,
      "narrow_total": 1004,
      "all_sedan": 329,
      "narrow_sedan": 329,
      "all_bus": 700,
      "narrow_bus": 675,
      "frames_with_gt": 588
    },
    "47": {
      "road": "highway",
      "time": "night",
      "weather": "heavysnow",
      "all_total": 258,
      "narrow_total": 151,
      "all_sedan": 105,
      "narrow_sedan": 84,
      "all_bus": 153,
      "narrow_bus": 67,
      "frames_with_gt": 244
    },
    "48": {
      "road": "highway",
      "time": "night",
      "weather": "lightsnow",
      "all_total": 1003,
      "narrow_total": 818,
      "all_sedan": 362,
      "narrow_sedan": 362,
      "all_bus": 641,
      "narrow_bus": 456,
      "frames_with_gt": 443
    },
    "49": {
      "road": "highway",
      "time": "night",
      "weather": "lightsnow",
      "all_total": 807,
      "narrow_total": 729,
      "all_sedan": 138,
      "narrow_sedan": 131,
      "all_bus": 669,
      "narrow_bus": 598,
      "frames_with_gt": 598
    },
    "50": {
      "road": "highway",
      "time": "night",
      "weather": "sleet",
      "all_total": 1076,
      "narrow_total": 613,
      "all_sedan": 1076,
      "narrow_sedan": 613,
      "all_bus": 0,
      "narrow_bus": 0,
      "frames_with_gt": 567
    },
    "51": {
      "road": "highway",
      "time": "night",
      "weather": "sleet",
      "all_total": 353,
      "narrow_total": 319,
      "all_sedan": 260,
      "narrow_sedan": 244,
      "all_bus": 93,
      "narrow_bus": 75,
      "frames_with_gt": 245
    },
    "52": {
      "road": "highway",
      "time": "night",
      "weather": "sleet",
      "all_total": 438,
      "narrow_total": 406,
      "all_sedan": 438,
      "narrow_sedan": 406,
      "all_bus": 0,
      "narrow_bus": 0,
      "frames_with_gt": 421
    },
    "53": {
      "road": "highway",
      "time": "day",
      "weather": "sleet",
      "all_total": 590,
      "narrow_total": 537,
      "all_sedan": 590,
      "narrow_sedan": 537,
      "all_bus": 0,
      "narrow_bus": 0,
      "frames_with_gt": 590
    }
  }
}